uv_secure/__init__.py
uv_secure/__version__.py
uv_secure/caching/__init__.py
uv_secure/caching/cache_manager.py
uv_secure/configuration/__init__.py
uv_secure/configuration/config_factory.py
uv_secure/configuration/configuration.py
uv_secure/configuration/exceptions.py
uv_secure/dependency_checker/__init__.py
uv_secure/dependency_checker/dependency_checker.py
uv_secure/directory_scanner/__init__.py
uv_secure/directory_scanner/directory_scanner.py
uv_secure/output_formatters/__init__.py
uv_secure/output_formatters/columns_formatter.py
uv_secure/output_formatters/formatter.py
uv_secure/output_formatters/json_formatter.py
uv_secure/output_models/__init__.py
uv_secure/output_models/output_models.py
uv_secure/package_info/__init__.py
uv_secure/package_info/dependency_file_parser.py
uv_secure/package_info/package_index_downloader.py
uv_secure/package_info/package_info_downloader.py
uv_secure/package_utils/__init__.py
uv_secure/package_utils/name_utils.py
uv_secure/py.typed
uv_secure/run.py
uv_secure-0.15.4.dist-info/WHEEL
uv_secure-0.15.4.dist-info/entry_points.txt
uv_secure-0.15.4.dist-info/METADATA
uv_secure-0.15.4.dist-info/RECORD
