Metadata-Version: 2.3
Name: uv-secure
Version: 0.15.4
Summary: Scan your uv.lock file for dependencies with known vulnerabilities
Keywords: uv,uv.lock,vulnerabilities
Author: Owen Lamont
Author-email: Owen Lamont <owenrlamont@gmail.com>
Classifier: Development Status :: 3 - Alpha
Classifier: Environment :: Console
Classifier: Intended Audience :: Developers
Classifier: Operating System :: OS Independent
Classifier: License :: OSI Approved :: MIT License
Classifier: Natural Language :: English
Classifier: Programming Language :: Python
Classifier: Programming Language :: Python :: 3.10
Classifier: Programming Language :: Python :: 3.11
Classifier: Programming Language :: Python :: 3.12
Classifier: Programming Language :: Python :: 3.13
Classifier: Programming Language :: Python :: 3.14
Classifier: Programming Language :: Python :: 3 :: Only
Classifier: Topic :: Software Development :: Quality Assurance
Classifier: Topic :: Software Development :: Testing
Classifier: Topic :: Software Development :: Libraries
Requires-Dist: anyio>=4.7.0
Requires-Dist: httpx>=0.28.1
Requires-Dist: humanize>=4.11.0
Requires-Dist: inflect>=7.4.0
Requires-Dist: orjson>=3.11.5
Requires-Dist: packaging>=25.0
Requires-Dist: pydantic[email]>=2.10.3
Requires-Dist: rich>=13.9.4
Requires-Dist: stamina>=25.1.0
Requires-Dist: tomli ; python_full_version < '3.11'
Requires-Dist: typer>=0.15.1
Requires-Dist: winloop>=0.1.8 ; sys_platform == 'win32' and extra == 'faster-async'
Requires-Dist: uvloop>=0.21.0 ; sys_platform != 'win32' and extra == 'faster-async'
Requires-Python: >=3.10
Project-URL: Releases, https://github.com/owenlamont/uv-secure/releases
Project-URL: Repository, https://github.com/owenlamont/uv-secure
Provides-Extra: faster-async
